password_strength_checker/__init__.py
password_strength_checker/checker.py
password_strength_checker/data/rockyou.txt.gz
tests/__init__.py
tests/test_checker.py
password_strength_checker_pro-1.0.0.2.dist-info/LICENSE
password_strength_checker_pro-1.0.0.2.dist-info/METADATA
password_strength_checker_pro-1.0.0.2.dist-info/WHEEL
password_strength_checker_pro-1.0.0.2.dist-info/top_level.txt
password_strength_checker_pro-1.0.0.2.dist-info/RECORD
