Metadata-Version: 2.1
Name: password_strength_checker_pro
Version: 1.0.0.2
Summary: A password strength checker with leak detection
Author: Oageng Motlapele
Author-email: oagengmtlapele@gmail.com
Classifier: Programming Language :: Python :: 3
Classifier: License :: OSI Approved :: MIT License
Classifier: Operating System :: OS Independent
Requires-Python: >=3.6
License-File: LICENSE
